image_metrics/__init__.py
image_metrics/analyze.py
imagemetrics/__init__.py
imagemetrics/analyze.py
imagemetrics-0.1.0.dist-info/METADATA
imagemetrics-0.1.0.dist-info/WHEEL
imagemetrics-0.1.0.dist-info/top_level.txt
imagemetrics-0.1.0.dist-info/RECORD
